quetzal/__init__.py
quetzal/augmentation.py
quetzal/cli.py
quetzal/optimization.py
quetzal_ai-1.0.8.dist-info/licenses/LICENSE
quetzal_ai-1.0.8.dist-info/METADATA
quetzal_ai-1.0.8.dist-info/WHEEL
quetzal_ai-1.0.8.dist-info/entry_points.txt
quetzal_ai-1.0.8.dist-info/top_level.txt
quetzal_ai-1.0.8.dist-info/RECORD
