Metadata-Version: 2.4
Name: quetzal-ai
Version: 1.0.8
Summary: Ultra-fast CPU training for low-resource languages
Author: Axya-Tech
Classifier: Development Status :: 4 - Beta
Classifier: Intended Audience :: Developers
Classifier: Intended Audience :: Science/Research
Classifier: License :: OSI Approved :: Apache Software License
Classifier: Programming Language :: Python :: 3
Classifier: Topic :: Scientific/Engineering :: Artificial Intelligence
Requires-Python: >=3.8
License-File: LICENSE
Requires-Dist: torch>=2.0.0
Requires-Dist: transformers>=4.36.0
Requires-Dist: tokenizers>=0.15.0
Requires-Dist: datasets>=2.14.0
Requires-Dist: accelerate>=0.25.0
Requires-Dist: peft>=0.7.0
Requires-Dist: bitsandbytes>=0.41.0
Requires-Dist: sentencepiece>=0.1.99
Requires-Dist: numpy>=1.24.0
Requires-Dist: tqdm>=4.65.0
Requires-Dist: scikit-learn>=1.3.0
Dynamic: author
Dynamic: classifier
Dynamic: description
Dynamic: description-content-type
Dynamic: license-file
Dynamic: requires-dist
Dynamic: requires-python
Dynamic: summary
